zufallsworte/__init__.py
zufallsworte-0.0.6.dist-info/LICENSE.txt
zufallsworte-0.0.6.dist-info/METADATA
zufallsworte-0.0.6.dist-info/WHEEL
zufallsworte-0.0.6.dist-info/top_level.txt
zufallsworte-0.0.6.dist-info/RECORD
